setup.py
total_ordering.py
total_ordering.egg-info/PKG-INFO
total_ordering.egg-info/SOURCES.txt
total_ordering.egg-info/dependency_links.txt
total_ordering.egg-info/not-zip-safe
total_ordering.egg-info/requires.txt
total_ordering.egg-info/top_level.txt