Metadata-Version: 1.1
Name: total-ordering
Version: 0.1.0
Summary: functools.total_ordering backport for Python 2.6
Home-page: https://github.com/kvesteri/total-ordering
Author: Konsta Vesterinen
Author-email: konsta@fastmonkeys.com
License: BSD
Platform: any
Classifier: Environment :: Web Environment
Classifier: Intended Audience :: Developers
Classifier: License :: OSI Approved :: BSD License
Classifier: Operating System :: OS Independent
Classifier: Programming Language :: Python
Classifier: Topic :: Internet :: WWW/HTTP :: Dynamic Content
Classifier: Topic :: Software Development :: Libraries :: Python Modules
